    "In method: public void updateEntities()
    @Opublic func_72939_s()V@|
    "Set limit before next method
    @Lpublic func_147448_a(Ljava/util/Collection;)V@|
    
    "---------PATCH ENTITIES LOOP-----------"
    ! Below:
        this.theProfiler.endStartSection("regular");
    !
    @SALOAD 0
    GETFIELD net/minecraft/world/World.field_72984_F : Lnet/minecraft/profiler/Profiler;
    LDC "regular"
    INVOKEVIRTUAL net/minecraft/profiler/Profiler.func_76318_c (Ljava/lang/String;)V@|
    
    ! Insert:
        com.wildex999.tickdynamic.TickDynamicMod.tickDynamic.getGroup("other").endTimer();
        com.wildex999.tickdynamic.timemanager.TimedEntities timedEntityGroup = com.wildex999.tickdynamic.TickDynamicMod.tickDynamic.getWorldEntities(this);
        timedEntityGroup.startTimer();
    !
    @+
    GETSTATIC com/wildex999/tickdynamic/TickDynamicMod.tickDynamic : Lcom/wildex999/tickdynamic/TickDynamicMod;
    LDC "other"
    INVOKEVIRTUAL com/wildex999/tickdynamic/TickDynamicMod.getGroup (Ljava/lang/String;)Lcom/wildex999/tickdynamic/timemanager/TimedGroup;
    INVOKEVIRTUAL com/wildex999/tickdynamic/timemanager/TimedGroup.endTimer ()V
    GETSTATIC com/wildex999/tickdynamic/TickDynamicMod.tickDynamic : Lcom/wildex999/tickdynamic/TickDynamicMod;
    ALOAD 0
    INVOKEVIRTUAL com/wildex999/tickdynamic/TickDynamicMod.getWorldEntities (Lnet/minecraft/world/World;)Lcom/wildex999/tickdynamic/timemanager/TimedEntities;
    ASTORE 21
    ALOAD 21
    INVOKEVIRTUAL com/wildex999/tickdynamic/timemanager/TimedEntities.startTimer ()V@E@|
    
    "Remove: i = 0
    @SL+
    LINENUMBER + L+@|
    @-
    ICONST_0
    ISTORE ?index]
   @|
    
    "Insert: i = timedEntityGroup.startUpdateObjects(this)
    @+
    ALOAD 21
    ALOAD 0
    INVOKEVIRTUAL com/wildex999/tickdynamic/timemanager/TimedEntities.startUpdateObjects (Lnet/minecraft/world/World;)I
    ISTORE =index]
   @|
    
    "Before: i < this.loadedEntityList.size()
    @EL+
   FRAME FULL +
    ILOAD =index]
    ALOAD 0
    GETFIELD net/minecraft/world/World.field_72996_f : Ljava/util/List;
    INVOKEINTERFACE java/util/List.size ()I
    IF_ICMPGE L+@|
    
    
    @SFRAME FULL +
    @|
    
    "Insert: i = timedEntityGroup.updateObjects(i);
    @+ALOAD 21
    ILOAD =index]
    INVOKEVIRTUAL com/wildex999/tickdynamic/timemanager/TimedEntities.updateObjects (I)I
    ISTORE =index]
    @|
    
    !Before: 
            this.theProfiler.endSection();
        }
        
        this.theProfiler.endStartSection("blockEntities");
    !
    @EALOAD 0
    GETFIELD net/minecraft/world/World.field_72984_F : Lnet/minecraft/profiler/Profiler;
    INVOKEVIRTUAL net/minecraft/profiler/Profiler.func_76319_b ()V
   L+
    LINENUMBER + L+
   FRAME FULL +
    IINC =index] 1
    GOTO L+
   L+
    LINENUMBER + L+
   FRAME FULL +
    ALOAD 0
    GETFIELD net/minecraft/world/World.field_72984_F : Lnet/minecraft/profiler/Profiler;
    LDC "blockEntities"@|
    
   @SFRAME FULL [net/minecraft/world/World I] []
    @|
    @+ALOAD 21
    INVOKEVIRTUAL com/wildex999/tickdynamic/timemanager/TimedEntities.endTimer ()V
    @|
    @EALOAD 0
    GETFIELD net/minecraft/world/World.field_72984_F : Lnet/minecraft/profiler/Profiler;
    LDC "blockEntities"
    INVOKEVIRTUAL net/minecraft/profiler/Profiler.func_76318_c (Ljava/lang/String;)V@|
    
    
    "---------PATCH TILE ENTITIES LOOP-----------"
    
    ! Below:
        this.theProfiler.endStartSection("blockEntities");
        this.field_147481_N = true;
    !
    @SALOAD 0
    GETFIELD net/minecraft/world/World.field_72984_F : Lnet/minecraft/profiler/Profiler;
    LDC "blockEntities"
    INVOKEVIRTUAL net/minecraft/profiler/Profiler.func_76318_c (Ljava/lang/String;)V
   L+
    LINENUMBER + L+
    ALOAD 0
    ICONST_1
    PUTFIELD net/minecraft/world/World.field_147481_N : Z
   L*@|
    !
      We end with star(*) since CoFHCore is adding it's own stuff between the end here and where we modify.
        com.wildex999.tickdynamic.timemanager.TimedTileEntities timedGroup = com.wildex999.tickdynamic.TickDynamicMod.tickDynamic.getWorldTileEntities(this);
        Iterator iterator = this.loadedTileEntityList.listIterator(timedGroup.startUpdateObjects(this));
        timedGroup.startTimer();
    !
    @-ALOAD 0
    GETFIELD net/minecraft/world/World.field_147482_g : Ljava/util/List;
    INVOKEINTERFACE java/util/List.iterator ()Ljava/util/Iterator;
    ASTORE ?iterator]@|
    @+GETSTATIC com/wildex999/tickdynamic/TickDynamicMod.tickDynamic : Lcom/wildex999/tickdynamic/TickDynamicMod;
    ALOAD 0
    INVOKEVIRTUAL com/wildex999/tickdynamic/TickDynamicMod.getWorldTileEntities (Lnet/minecraft/world/World;)Lcom/wildex999/tickdynamic/timemanager/TimedTileEntities;
    ASTORE 20
    ALOAD 0
    GETFIELD net/minecraft/world/World.field_147482_g : Ljava/util/List;
    ALOAD 20
    ALOAD 0
    INVOKEVIRTUAL com/wildex999/tickdynamic/timemanager/TimedTileEntities.startUpdateObjects (Lnet/minecraft/world/World;)I
    INVOKEINTERFACE java/util/List.listIterator (I)Ljava/util/ListIterator;
    ASTORE =iterator]
    ALOAD 20
    INVOKEVIRTUAL com/wildex999/tickdynamic/timemanager/TimedTileEntities.startTimer ()V@E@|
    
    "----------------------"
    
    
    @SL+
    LINENUMBER + L+
   FRAME FULL +
    @|
    
    "Insert: iterator = timedGroup.updateObjects(iterator);
    @+ALOAD 20
    ALOAD =iterator]
    INVOKEVIRTUAL com/wildex999/tickdynamic/timemanager/TimedTileEntities.updateObjects (Ljava/util/Iterator;)Ljava/util/Iterator;
    ASTORE =iterator]
    @|
    
    "Before iterator.hasNext()
    @EALOAD =iterator]
    INVOKEINTERFACE java/util/Iterator.hasNext ()Z
    IFEQ +
   L+
    LINENUMBER + L+
    ALOAD =iterator]
    INVOKEINTERFACE java/util/Iterator.next ()Ljava/lang/Object;
    CHECKCAST net/minecraft/tileentity/TileEntity
    ASTORE +@|
    
    "----------------------"
    
    !Insert: 
        timedGroup.endTimer(loadedTileEntityList.size());
        com.wildex999.tickdynamic.TickDynamicMod.tickDynamic.getGroup("other").startTimer();
    !
    @S
    @+ALOAD 20
    INVOKEVIRTUAL com/wildex999/tickdynamic/timemanager/TimedTileEntities.endTimer ()V
    GETSTATIC com/wildex999/tickdynamic/TickDynamicMod.tickDynamic : Lcom/wildex999/tickdynamic/TickDynamicMod;
    LDC "other"
    INVOKEVIRTUAL com/wildex999/tickdynamic/TickDynamicMod.getGroup (Ljava/lang/String;)Lcom/wildex999/tickdynamic/timemanager/TimedGroup;
    INVOKEVIRTUAL com/wildex999/tickdynamic/timemanager/TimedGroup.startTimer ()V
    @|
    
    "Before: if (!this.field_147483_b.isEmpty())
    @EALOAD 0
    GETFIELD net/minecraft/world/World.field_147483_b : Ljava/util/List;
    INVOKEINTERFACE java/util/List.isEmpty ()Z
    IFNE L+@|
    
    